[
  {
    "name": "Tarjetas adicionales",
    "description": "TELEFONICA",
    "icon": "assets/img/pay-services/wallet.svg"
  },
  {
    "name": "Seguro Item personales",
    "description": "NETFLIX",
    "icon": "assets/img/pay-services/key.svg"
  },
  {
    "name": "Ampliación línea crédito",
    "description": "CENCOSUD",
    "icon": "assets/img/pay-services/card.svg"
  },
  {
    "name": "Seguro de auto",
    "description": "ECOGAS",
    "icon": "assets/img/pay-services/car.svg"
  },

  {
    "name": "Seguro de hogar",
    "description": "TELEFONICA",
    "icon": "assets/img/pay-services/home.svg"
  }
]
